Workbook

Sheet Sales Data
A1: SALES DATA ANALYSIS + PROFESSIONAL DASHBOARD
A2: Raw Sales Transactions | Jan 2025 – Jun 2025 | Live formula-based sheet
A4: Date | B4: Order ID | C4: Customer | D4: Product | E4: Category | F4: Region | G4: Salesperson | H4: Quantity | I4: Unit Price (₹) | J4: Cost (₹) | K4: Revenue (₹) | L4: Total Cost (₹) | M4: Profit (₹) | N4: Month
A5: 45658 | B5: ORD1003 | C5: Aggarwal Retail | D5: Laptop | E5: Computers | F5: North | G5: Farhan Ali | H5: 4 | I5: 45000 | J5: 38000 | K5: =H5*I5 -> 180000 | L5: =H5*J5 -> 152000 | M5: =K5-L5 -> 28000 | N5: =TEXT(A5,"mmm-yyyy") -> Jan-2025
A6: 45664 | B6: ORD1004 | C6: Orbit Systems | D6: Webcam | E6: Accessories | F6: East | G6: Rohan Mehta | H6: 4 | I6: 1520 | J6: 1000 | K6: =H6*I6 -> 6080 | L6: =H6*J6 -> 4000 | M6: =K6-L6 -> 2080 | N6: =TEXT(A6,"mmm-yyyy") -> Jan-2025
A7: 45675 | B7: ORD1008 | C7: Aggarwal Retail | D7: Laptop | E7: Computers | F7: East | G7: Farhan Ali | H7: 2 | I7: 45500 | J7: 38000 | K7: =H7*I7 -> 91000 | L7: =H7*J7 -> 76000 | M7: =K7-L7 -> 15000 | N7: =TEXT(A7,"mmm-yyyy") -> Jan-2025
A8: 45678 | B8: ORD1001 | C8: Bansal Electronics | D8: Laptop | E8: Computers | F8: South | G8: Ayesha Khan | H8: 5 | I8: 44500 | J8: 38000 | K8: =H8*I8 -> 222500 | L8: =H8*J8 -> 190000 | M8: =K8-L8 -> 32500 | N8: =TEXT(A8,"mmm-yyyy") -> Jan-2025
A9: 45681 | B9: ORD1002 | C9: Trident Corp | D9: Laptop | E9: Computers | F9: West | G9: Rohan Mehta | H9: 2 | I9: 46000 | J9: 38000 | K9: =H9*I9 -> 92000 | L9: =H9*J9 -> 76000 | M9: =K9-L9 -> 16000 | N9: =TEXT(A9,"mmm-yyyy") -> Jan-2025
A10: 45682 | B10: ORD1005 | C10: Nexa Solutions | D10: Monitor | E10: Computers | F10: South | G10: Ayesha Khan | H10: 6 | I10: 9500 | J10: 7000 | K10: =H10*I10 -> 57000 | L10: =H10*J10 -> 42000 | M10: =K10-L10 -> 15000 | N10: =TEXT(A10,"mmm-yyyy") -> Jan-2025
A11: 45682 | B11: ORD1006 | C11: Kapoor Digital | D11: Printer | E11: Computers | F11: North | G11: Karan Singh | H11: 2 | I11: 11500 | J11: 9500 | K11: =H11*I11 -> 23000 | L11: =H11*J11 -> 19000 | M11: =K11-L11 -> 4000 | N11: =TEXT(A11,"mmm-yyyy") -> Jan-2025
A12: 45685 | B12: ORD1007 | C12: Malhotra Traders | D12: Printer | E12: Computers | F12: North | G12: Divya Nair | H12: 5 | I12: 13000 | J12: 9500 | K12: =H12*I12 -> 65000 | L12: =H12*J12 -> 47500 | M12: =K12-L12 -> 17500 | N12: =TEXT(A12,"mmm-yyyy") -> Jan-2025
A13: 45685 | B13: ORD1009 | C13: BrightPath Ltd | D13: Printer | E13: Computers | F13: North | G13: Rohan Mehta | H13: 4 | I13: 13000 | J13: 9500 | K13: =H13*I13 -> 52000 | L13: =H13*J13 -> 38000 | M13: =K13-L13 -> 14000 | N13: =TEXT(A13,"mmm-yyyy") -> Jan-2025
A14: 45695 | B14: ORD1012 | C14: Trident Corp | D14: Webcam | E14: Accessories | F14: South | G14: Farhan Ali | H14: 2 | I14: 1500 | J14: 1000 | K14: =H14*I14 -> 3000 | L14: =H14*J14 -> 2000 | M14: =K14-L14 -> 1000 | N14: =TEXT(A14,"mmm-yyyy") -> Feb-2025
A15: 45696 | B15: ORD1014 | C15: Bansal Electronics | D15: Webcam | E15: Accessories | F15: North | G15: Karan Singh | H15: 1 | I15: 1500 | J15: 1000 | K15: =H15*I15 -> 1500 | L15: =H15*J15 -> 1000 | M15: =K15-L15 -> 500 | N15: =TEXT(A15,"mmm-yyyy") -> Feb-2025
A16: 45696 | B16: ORD1017 | C16: Kapoor Digital | D16: Webcam | E16: Accessories | F16: West | G16: Karan Singh | H16: 10 | I16: 1500 | J16: 1000 | K16: =H16*I16 -> 15000 | L16: =H16*J16 -> 10000 | M16: =K16-L16 -> 5000 | N16: =TEXT(A16,"mmm-yyyy") -> Feb-2025
... A54: 45825 | B54: ORD1045 | C54: Trident Corp | D54: Laptop | E54: Computers | F54: North | G54: Ayesha Khan | H54: 2 | I54: 45000 | J54: 38000 | K54: =H54*I54 -> 90000 | L54: =H54*J54 -> 76000 | M54: =K54-L54 -> 14000 | N54: =TEXT(A54,"mmm-yyyy") -> Jun-2025
A56: Formula Logic
A57: • Revenue = Quantity × Unit Price
A58: • Total Cost = Quantity × Cost
A59: • Profit = Revenue − Total Cost
A60: • Month = auto-extracted from Date, used to group the Month-wise summary

Sheet Analysis
A1: SALES ANALYSIS SUMMARY
A3: Product-wise Summary
A4: Product | B4: Orders | C4: Quantity Sold | D4: Revenue (₹) | E4: Profit (₹)
A5: Laptop | B5: =COUNTIF('Sales Data'!D5:D54,A5) -> 11 | C5: =SUMIFS('Sales Data'!H5:H54,'Sales Data'!D5:D54,A5) -> 53 | D5: =SUMIFS('Sales Data'!K5:K54,'Sales Data'!D5:D54,A5) -> 2403000 | E5: =SUMIFS('Sales Data'!M5:M54,'Sales Data'!D5:D54,A5) -> 389000
A6: Monitor | B6: =COUNTIF('Sales Data'!D5:D54,A6) -> 8 | C6: =SUMIFS('Sales Data'!H5:H54,'Sales Data'!D5:D54,A6) -> 46 | D6: =SUMIFS('Sales Data'!K5:K54,'Sales Data'!D5:D54,A6) -> 444500 | E6: =SUMIFS('Sales Data'!M5:M54,'Sales Data'!D5:D54,A6) -> 122500
A7: Printer | B7: =COUNTIF('Sales Data'!D5:D54,A7) -> 8 | C7: =SUMIFS('Sales Data'!H5:H54,'Sales Data'!D5:D54,A7) -> 37 | D7: =SUMIFS('Sales Data'!K5:K54,'Sales Data'!D5:D54,A7) -> 465500 | E7: =SUMIFS('Sales Data'!M5:M54,'Sales Data'!D5:D54,A7) -> 114000
A8: Keyboard | B8: =COUNTIF('Sales Data'!D5:D54,A8) -> 10 | C8: =SUMIFS('Sales Data'!H5:H54,'Sales Data'!D5:D54,A8) -> 41 | D8: =SUMIFS('Sales Data'!K5:K54,'Sales Data'!D5:D54,A8) -> 32720 | E8: =SUMIFS('Sales Data'!M5:M54,'Sales Data'!D5:D54,A8) -> 12220
A9: Mouse | B9: =COUNTIF('Sales Data'!D5:D54,A9) -> 4 | C9: =SUMIFS('Sales Data'!H5:H54,'Sales Data'!D5:D54,A9) -> 30 | D9: =SUMIFS('Sales Data'!K5:K54,'Sales Data'!D5:D54,A9) -> 15180 | E9: =SUMIFS('Sales Data'!M5:M54,'Sales Data'!D5:D54,A9) -> 6180
A10: Webcam | B10: =COUNTIF('Sales Data'!D5:D54,A10) -> 9 | C10: =SUMIFS('Sales Data'!H5:H54,'Sales Data'!D5:D54,A10) -> 44 | D10: =SUMIFS('Sales Data'!K5:K54,'Sales Data'!D5:D54,A10) -> 66000 | E10: =SUMIFS('Sales Data'!M5:M54,'Sales Data'!D5:D54,A10) -> 22000
A13: Region-wise Summary
A14: Region | B14: Orders | C14: Quantity Sold | D14: Revenue (₹) | E14: Profit (₹)
A15: North | B15: =COUNTIF('Sales Data'!F5:F54,A15) -> 18 | C15: =SUMIFS('Sales Data'!H5:H54,'Sales Data'!F5:F54,A15) -> 94 | D15: =SUMIFS('Sales Data'!K5:K54,'Sales Data'!F5:F54,A15) -> 1667040 | E15: =SUMIFS('Sales Data'!M5:M54,'Sales Data'!F5:F54,A15) -> 311840
A16: South | B16: =COUNTIF('Sales Data'!F5:F54,A16) -> 12 | C16: =SUMIFS('Sales Data'!H5:H54,'Sales Data'!F5:F54,A16) -> 63 | D16: =SUMIFS('Sales Data'!K5:K54,'Sales Data'!F5:F54,A16) -> 938460 | E16: =SUMIFS('Sales Data'!M5:M54,'Sales Data'!F5:F54,A16) -> 192960
A17: East | B17: =COUNTIF('Sales Data'!F5:F54,A17) -> 12 | C17: =SUMIFS('Sales Data'!H5:H54,'Sales Data'!F5:F54,A17) -> 62 | D17: =SUMIFS('Sales Data'!K5:K54,'Sales Data'!F5:F54,A17) -> 322300 | E17: =SUMIFS('Sales Data'!M5:M54,'Sales Data'!F5:F54,A17) -> 71000
A18: West | B18: =COUNTIF('Sales Data'!F5:F54,A18) -> 8 | C18: =SUMIFS('Sales Data'!H5:H54,'Sales Data'!F5:F54,A18) -> 32 | D18: =SUMIFS('Sales Data'!K5:K54,'Sales Data'!F5:F54,A18) -> 499100 | E18: =SUMIFS('Sales Data'!M5:M54,'Sales Data'!F5:F54,A18) -> 90100
A21: Month-wise Summary
A22: Month | B22: Orders | C22: Quantity Sold | D22: Revenue (₹) | E22: Profit (₹)
A23: Jan-2025 | B23: =COUNTIF('Sales Data'!N5:N54,A23) -> 9 | C23: =SUMIFS('Sales Data'!H5:H54,'Sales Data'!N5:N54,A23) -> 34 | D23: =SUMIFS('Sales Data'!K5:K54,'Sales Data'!N5:N54,A23) -> 788580 | E23: =SUMIFS('Sales Data'!M5:M54,'Sales Data'!N5:N54,A23) -> 144080
A24: Feb-2025 | B24: =COUNTIF('Sales Data'!N5:N54,A24) -> 8 | C24: =SUMIFS('Sales Data'!H5:H54,'Sales Data'!N5:N54,A24) -> 41 | D24: =SUMIFS('Sales Data'!K5:K54,'Sales Data'!N5:N54,A24) -> 237060 | E24: =SUMIFS('Sales Data'!M5:M54,'Sales Data'!N5:N54,A24) -> 55060
A25: Mar-2025 | B25: =COUNTIF('Sales Data'!N5:N54,A25) -> 9 | C25: =SUMIFS('Sales Data'!H5:H54,'Sales Data'!N5:N54,A25) -> 65 | D25: =SUMIFS('Sales Data'!K5:K54,'Sales Data'!N5:N54,A25) -> 657140 | E25: =SUMIFS('Sales Data'!M5:M54,'Sales Data'!N5:N54,A25) -> 134140
A26: Apr-2025 | B26: =COUNTIF('Sales Data'!N5:N54,A26) -> 8 | C26: =SUMIFS('Sales Data'!H5:H54,'Sales Data'!N5:N54,A26) -> 51 | D26: =SUMIFS('Sales Data'!K5:K54,'Sales Data'!N5:N54,A26) -> 392040 | E26: =SUMIFS('Sales Data'!M5:M54,'Sales Data'!N5:N54,A26) -> 97540
A27: May-2025 | B27: =COUNTIF('Sales Data'!N5:N54,A27) -> 8 | C27: =SUMIFS('Sales Data'!H5:H54,'Sales Data'!N5:N54,A27) -> 31 | D27: =SUMIFS('Sales Data'!K5:K54,'Sales Data'!N5:N54,A27) -> 670520 | E27: =SUMIFS('Sales Data'!M5:M54,'Sales Data'!N5:N54,A27) -> 115020
A28: Jun-2025 | B28: =COUNTIF('Sales Data'!N5:N54,A28) -> 8 | C28: =SUMIFS('Sales Data'!H5:H54,'Sales Data'!N5:N54,A28) -> 29 | D28: =SUMIFS('Sales Data'!K5:K54,'Sales Data'!N5:N54,A28) -> 681560 | E28: =SUMIFS('Sales Data'!M5:M54,'Sales Data'!N5:N54,A28) -> 120060

Sheet Dashboard
A1: SALES DASHBOARD
A3: TOTAL SALES | C3: TOTAL PROFIT | E3: TOTAL ORDERS | G3: AVG ORDER VALUE (₹)
A4: =SUM('Sales Data'!K5:K54) -> 3426900 | C4: =SUM('Sales Data'!M5:M54) -> 665900 | E4: =COUNTA('Sales Data'!B5:B54) -> 50 | G4: =SUM('Sales Data'!K5:K54)/COUNTA('Sales Data'!B5:B54) -> 68538
