Workbook

Sheet Sales Data
A1: SMALL SHOP SALES & PROFIT MANAGER
A2: Daily Sales Register | 01-Sep-26 to 15-Sep-26 | Live formula-based sheet
A4: Date | B4: Product | C4: Category | D4: Qty | E4: Purchase Price (₹) | F4: Selling Price (₹) | G4: Sales (₹) | H4: Cost (₹) | I4: Profit (₹) | J4: Profit %
A5: 46266 | B5: Pencil | C5: Stationery | D5: 28 | E5: 3 | F5: 6 | G5: =D5*F5 -> 168 | H5: =D5*E5 -> 84 | I5: =G5-H5 -> 84 | J5: =I5/H5*100 -> 100
A6: 46266 | B6: Umbrella | C6: General | D6: 3 | E6: 150 | F6: 220 | G6: =D6*F6 -> 660 | H6: =D6*E6 -> 450 | I6: =G6-H6 -> 210 | J6: =I6/H6*100 -> 46.666667
A7: 46266 | B7: Pen | C7: Stationery | D7: 55 | E7: 5 | F7: 10 | G7: =D7*F7 -> 550 | H7: =D7*E7 -> 275 | I7: =G7-H7 -> 275 | J7: =I7/H7*100 -> 100
A8: 46267 | B8: Pen | C8: Stationery | D8: 26 | E8: 5 | F8: 10 | G8: =D8*F8 -> 260 | H8: =D8*E8 -> 130 | I8: =G8-H8 -> 130 | J8: =I8/H8*100 -> 100
A9: 46267 | B9: Bottle | C9: General | D9: 3 | E9: 80 | F9: 120 | G9: =D9*F9 -> 360 | H9: =D9*E9 -> 240 | I9: =G9-H9 -> 120 | J9: =I9/H9*100 -> 50
A10: 46267 | B10: Biscuit Pack | C10: General | D10: 18 | E10: 20 | F10: 30 | G10: =D10*F10 -> 540 | H10: =D10*E10 -> 360 | I10: =G10-H10 -> 180 | J10: =I10/H10*100 -> 50
A11: 46267 | B11: Eraser | C11: Stationery | D11: 5 | E11: 2 | F11: 5 | G11: =D11*F11 -> 25 | H11: =D11*E11 -> 10 | I11: =G11-H11 -> 15 | J11: =I11/H11*100 -> 150
A12: 46268 | B12: Stapler | C12: Stationery | D12: 29 | E12: 45 | F12: 70 | G12: =D12*F12 -> 2030 | H12: =D12*E12 -> 1305 | I12: =G12-H12 -> 725 | J12: =I12/H12*100 -> 55.555556
A13: 46268 | B13: Pen | C13: Stationery | D13: 18 | E13: 5 | F13: 10 | G13: =D13*F13 -> 180 | H13: =D13*E13 -> 90 | I13: =G13-H13 -> 90 | J13: =I13/H13*100 -> 100
A14: 46268 | B14: Pen | C14: Stationery | D14: 38 | E14: 5 | F14: 10 | G14: =D14*F14 -> 380 | H14: =D14*E14 -> 190 | I14: =G14-H14 -> 190 | J14: =I14/H14*100 -> 100
A15: 46269 | B15: Notebook | C15: Stationery | D15: 55 | E15: 25 | F15: 40 | G15: =D15*F15 -> 2200 | H15: =D15*E15 -> 1375 | I15: =G15-H15 -> 825 | J15: =I15/H15*100 -> 60
A16: 46269 | B16: Bottle | C16: General | D16: 5 | E16: 80 | F16: 120 | G16: =D16*F16 -> 600 | H16: =D16*E16 -> 400 | I16: =G16-H16 -> 200 | J16: =I16/H16*100 -> 50
... A54: 46280 | B54: Geometry Box | C54: Stationery | D54: 40 | E54: 55 | F54: 85 | G54: =D54*F54 -> 3400 | H54: =D54*E54 -> 2200 | I54: =G54-H54 -> 1200 | J54: =I54/H54*100 -> 54.545455
A56: Formula Logic
A57: • Sales = Qty × Selling Price
A58: • Cost = Qty × Purchase Price
A59: • Profit = Sales − Cost
A60: • Profit % = (Profit ÷ Cost) × 100

Sheet Dashboard
A1: SHOP PROFIT DASHBOARD
A3: TOTAL SALES | C3: TOTAL COST | E3: TOTAL PROFIT | G3: PROFIT % | I3: BEST PRODUCT
A4: =SUM('Sales Data'!G5:G54) -> 50234 | C4: =SUM('Sales Data'!H5:H54) -> 31815 | E4: =SUM('Sales Data'!I5:I54) -> 18419 | G4: =SUM('Sales Data'!I5:I54)/SUM('Sales Data'!H5:H54)*100 -> 57.894075 | I4: =INDEX(A22:A36,MATCH(MAX(E22:E36),E22:E36,0)) -> Geometry Box
A20: Product-wise Summary
A21: Product | B21: Qty Sold | C21: Sales (₹) | D21: Cost (₹) | E21: Profit (₹)
A22: Notebook | B22: =SUMIFS('Sales Data'!D5:D54,'Sales Data'!B5:B54,A22) -> 55 | C22: =SUMIFS('Sales Data'!G5:G54,'Sales Data'!B5:B54,A22) -> 2200 | D22: =SUMIFS('Sales Data'!H5:H54,'Sales Data'!B5:B54,A22) -> 1375 | E22: =SUMIFS('Sales Data'!I5:I54,'Sales Data'!B5:B54,A22) -> 825
A23: Pen | B23: =SUMIFS('Sales Data'!D5:D54,'Sales Data'!B5:B54,A23) -> 329 | C23: =SUMIFS('Sales Data'!G5:G54,'Sales Data'!B5:B54,A23) -> 3290 | D23: =SUMIFS('Sales Data'!H5:H54,'Sales Data'!B5:B54,A23) -> 1645 | E23: =SUMIFS('Sales Data'!I5:I54,'Sales Data'!B5:B54,A23) -> 1645
A24: Pencil | B24: =SUMIFS('Sales Data'!D5:D54,'Sales Data'!B5:B54,A24) -> 99 | C24: =SUMIFS('Sales Data'!G5:G54,'Sales Data'!B5:B54,A24) -> 594 | D24: =SUMIFS('Sales Data'!H5:H54,'Sales Data'!B5:B54,A24) -> 297 | E24: =SUMIFS('Sales Data'!I5:I54,'Sales Data'!B5:B54,A24) -> 297
A25: Eraser | B25: =SUMIFS('Sales Data'!D5:D54,'Sales Data'!B5:B54,A25) -> 53 | C25: =SUMIFS('Sales Data'!G5:G54,'Sales Data'!B5:B54,A25) -> 265 | D25: =SUMIFS('Sales Data'!H5:H54,'Sales Data'!B5:B54,A25) -> 106 | E25: =SUMIFS('Sales Data'!I5:I54,'Sales Data'!B5:B54,A25) -> 159
A26: Sharpener | B26: =SUMIFS('Sales Data'!D5:D54,'Sales Data'!B5:B54,A26) -> 29 | C26: =SUMIFS('Sales Data'!G5:G54,'Sales Data'!B5:B54,A26) -> 203 | D26: =SUMIFS('Sales Data'!H5:H54,'Sales Data'!B5:B54,A26) -> 87 | E26: =SUMIFS('Sales Data'!I5:I54,'Sales Data'!B5:B54,A26) -> 116
A27: Register | B27: =SUMIFS('Sales Data'!D5:D54,'Sales Data'!B5:B54,A27) -> 119 | C27: =SUMIFS('Sales Data'!G5:G54,'Sales Data'!B5:B54,A27) -> 8330 | D27: =SUMIFS('Sales Data'!H5:H54,'Sales Data'!B5:B54,A27) -> 5355 | E27: =SUMIFS('Sales Data'!I5:I54,'Sales Data'!B5:B54,A27) -> 2975
A28: Stapler | B28: =SUMIFS('Sales Data'!D5:D54,'Sales Data'!B5:B54,A28) -> 53 | C28: =SUMIFS('Sales Data'!G5:G54,'Sales Data'!B5:B54,A28) -> 3710 | D28: =SUMIFS('Sales Data'!H5:H54,'Sales Data'!B5:B54,A28) -> 2385 | E28: =SUMIFS('Sales Data'!I5:I54,'Sales Data'!B5:B54,A28) -> 1325
A29: Geometry Box | B29: =SUMIFS('Sales Data'!D5:D54,'Sales Data'!B5:B54,A29) -> 126 | C29: =SUMIFS('Sales Data'!G5:G54,'Sales Data'!B5:B54,A29) -> 10710 | D29: =SUMIFS('Sales Data'!H5:H54,'Sales Data'!B5:B54,A29) -> 6930 | E29: =SUMIFS('Sales Data'!I5:I54,'Sales Data'!B5:B54,A29) -> 3780
A30: File Folder | B30: =SUMIFS('Sales Data'!D5:D54,'Sales Data'!B5:B54,A30) -> 167 | C30: =SUMIFS('Sales Data'!G5:G54,'Sales Data'!B5:B54,A30) -> 4175 | D30: =SUMIFS('Sales Data'!H5:H54,'Sales Data'!B5:B54,A30) -> 2505 | E30: =SUMIFS('Sales Data'!I5:I54,'Sales Data'!B5:B54,A30) -> 1670
A31: Bottle | B31: =SUMIFS('Sales Data'!D5:D54,'Sales Data'!B5:B54,A31) -> 55 | C31: =SUMIFS('Sales Data'!G5:G54,'Sales Data'!B5:B54,A31) -> 6600 | D31: =SUMIFS('Sales Data'!H5:H54,'Sales Data'!B5:B54,A31) -> 4400 | E31: =SUMIFS('Sales Data'!I5:I54,'Sales Data'!B5:B54,A31) -> 2200
A32: Umbrella | B32: =SUMIFS('Sales Data'!D5:D54,'Sales Data'!B5:B54,A32) -> 22 | C32: =SUMIFS('Sales Data'!G5:G54,'Sales Data'!B5:B54,A32) -> 4840 | D32: =SUMIFS('Sales Data'!H5:H54,'Sales Data'!B5:B54,A32) -> 3300 | E32: =SUMIFS('Sales Data'!I5:I54,'Sales Data'!B5:B54,A32) -> 1540
A33: Lunch Box | B33: =SUMIFS('Sales Data'!D5:D54,'Sales Data'!B5:B54,A33) -> 25 | C33: =SUMIFS('Sales Data'!G5:G54,'Sales Data'!B5:B54,A33) -> 3500 | D33: =SUMIFS('Sales Data'!H5:H54,'Sales Data'!B5:B54,A33) -> 2250 | E33: =SUMIFS('Sales Data'!I5:I54,'Sales Data'!B5:B54,A33) -> 1250
A34: Mug | B34: =SUMIFS('Sales Data'!D5:D54,'Sales Data'!B5:B54,A34) -> 7 | C34: =SUMIFS('Sales Data'!G5:G54,'Sales Data'!B5:B54,A34) -> 245 | D34: =SUMIFS('Sales Data'!H5:H54,'Sales Data'!B5:B54,A34) -> 140 | E34: =SUMIFS('Sales Data'!I5:I54,'Sales Data'!B5:B54,A34) -> 105
A35: Detergent Soap | B35: =SUMIFS('Sales Data'!D5:D54,'Sales Data'!B5:B54,A35) -> 6 | C35: =SUMIFS('Sales Data'!G5:G54,'Sales Data'!B5:B54,A35) -> 192 | D35: =SUMIFS('Sales Data'!H5:H54,'Sales Data'!B5:B54,A35) -> 120 | E35: =SUMIFS('Sales Data'!I5:I54,'Sales Data'!B5:B54,A35) -> 72
A36: Biscuit Pack | B36: =SUMIFS('Sales Data'!D5:D54,'Sales Data'!B5:B54,A36) -> 46 | C36: =SUMIFS('Sales Data'!G5:G54,'Sales Data'!B5:B54,A36) -> 1380 | D36: =SUMIFS('Sales Data'!H5:H54,'Sales Data'!B5:B54,A36) -> 920 | E36: =SUMIFS('Sales Data'!I5:I54,'Sales Data'!B5:B54,A36) -> 460
